plistop.py
plistop-0.2.dist-info/METADATA
plistop-0.2.dist-info/SOURCES 2.txt
plistop-0.2.dist-info/WHEEL
plistop-0.2.dist-info/top_level.txt
plistop-0.2.dist-info/RECORD
